Workbook
Name Slicer_Recommended_Action: #N/A

Sheet README
B1: Fashion E-Commerce · Sell-Through & Assortment Model
B2: Commercial analysis project - Synthetic Data
B4: OVERVIEW
B5: A commercial-analyst working model that turns weekly sales and stock data into concrete buying actions: what to reorder, what to mark down, and where sales are being lost to stock-outs. Built on sysnthetic data.
B7: HEADLINE FINDINGS
B8: -Overall sell-through reached 77.6%
B9: -An estimated €98k of revenue was lost to stock-outs: 42 SKU/channel combinations sold out before season end, concentrated in seasonal dresses.
B10: -28 SKU/channel combinations are markdown candidates (outerwear in particular sits at ~54% sell-through with capital tied up in unsold stock).
B11: -The pattern is a buying imbalance: money was over-committed to slow categories and under-committed to the styles customers actually wanted.
B13: STRUCTURE
B14: -Dashboard: headline KPIs, channel and category performance, a sell-through vs weeks-of-cover quadrant, and ranked reorder / markdown / missed-sales lists.
B15: -Assumptions : every decision threshold in one place.
... B34: BENCHMARK CALIBRATION
B35: Parameter | C35: Model | D35: Published benchmark | E35: Source
B36: Overall sell-through | C36: 77.6% | D36: Apparel & fashion: 65–85% | E36: Toolio
B37: Target sell-through (reorder) | C37: 80% | D37: Benchmark STR at or above 80%; >80% for short-life drops | E37: Shopify
B38: Markdown sell-through ceiling | C38: 60% | D38: End-of-season STR below 60% triggers markdown escalation | E38: Toolio
B39: Target weeks of cover | C39: 6 | D39: Fast fashion runs a lean 4–6 weeks of cover | E39: StyleMatrix
B40: Reorder cover vs lead time | C40: 3 vs 2 wks | D40: Reorder keyed to whether cover exceeds lead time | E40: Reactive SDP
B41: Full-price sell-through context | C41: — | D41: ~70% full-price sell-through before first markdown | E41: nul.global
B43: SOURCES
B44: Toolio — Sell-Through Rate: Formula, Benchmarks & Strategies to Improve It.
B45: https://www.toolio.com/post/sell-through-rate-how-to-calculate-and-5-strategies-to-optimize
B46: Shopify — Sell-Through Rate (STR): How to Calculate & Improve It.
B47: https://www.shopify.com/blog/sell-through-rate
B48: StyleMatrix — Weeks of Cover: How Much Stock Should You Hold?
B49: https://stylematrix.io/weeks-of-cover-retail-how-much-stock-should-you-hold/
B50: Reactive SDP — Weeks of Cover: The Metric Every Retail Buyer Should Obsess Over.
B51: https://reactivesdp.com/blog/weeks-of-cover-retail-planning.html
B52: nul.global — Sell-Through in Fashion: Benchmarks & Optimization.
B53: https://nul.global/blog/sell-through-in-fashion
B55: Accessed July 2026

Sheet Dashboard
A1: Sell-Through & Assortment Dashboard
A4: TOTAL UNITS SOLD | D4: REVENUE (SOLD) | G4: OVERALL SELL-THROUGH | J4: STOCK-OUTS (SKU x CHANNEL)
A5: =SUM(Analysis!$I$2:$I$121) -> 13422 | D5: =SUMPRODUCT(Analysis!$I$2:$I$121,Analysis!$G$2:$G$121) -> 551396.78 | G5: =SUM(Analysis!$I$2:$I$121)/SUM(Analysis!$H$2:$H$121) -> 0.77637668 | J5: =SUM(Analysis!$Q$2:$Q$121) -> 42
A8: SKUs x CHANNEL TO REORDER | D8: REORDER UNITS | G8: MARKDOWN CANDIDATES (x CHANNEL) | J8: EST. MISSED REVENUE
A9: =SUM(Analysis!$U$2:$U$121) -> 72 | D9: =SUM(Analysis!$W$2:$W$121) -> 7672 | G9: =SUM(Analysis!$V$2:$V$121) -> 28 | J9: =SUM(Analysis!$T$2:$T$121) -> 98288.119
A12: CHANNEL PERFORMANCE | I12: CATEGORY PERFORMANCE
A13: Channel | B13: Units Sold | C13: Received | D13: Sell-Through | E13: Revenue € | F13: Reorder Units | G13: Missed Rev € | I13: Category | J13: Units Sold | K13: Sell-Through | L13: End Stock | M13: Markdown SKUs
A14: Own Site | B14: =SUMIFS(Analysis!$I$2:$I$121,Analysis!$B$2:$B$121,$A14) -> 3110 | C14: =SUMIFS(Analysis!$H$2:$H$121,Analysis!$B$2:$B$121,$A14) -> 4043 | D14: =B14/C14 -> 0.76923077 | E14: =SUMPRODUCT((Analysis!$B$2:$B$121=$A14)*Analysis!$I$2:$I$121*Analysis!$G$2:$G$121) -> 127810.9 | F14: =SUMIFS(Analysis!$W$2:$W$121,Analysis!$B$2:$B$121,$A14) -> 1660 | G14: =SUMIFS(Analysis!$T$2:$T$121,Analysis!$B$2:$B$121,$A14) -> 22124.672 | I14: Dresses | J14: =SUMIFS(Analysis!$I$2:$I$121,Analysis!$D$2:$D$121,$I14) -> 3040 | K14: =SUMIFS(Analysis!$I$2:$I$121,Analysis!$D$2:$D$121,$I14)/SUMIFS(Analysis!$H$2:$H$121,Analysis!$D$2:$D$121,$I14) -> 0.80657999 | L14: =SUMIFS(Analysis!$J$2:$J$121,Analysis!$D$2:$D$121,$I14) -> 729 | M14: =SUMIFS(Analysis!$V$2:$V$121,Analysis!$D$2:$D$121,$I14) -> 8
A15: Marketplace Alpha | B15: =SUMIFS(Analysis!$I$2:$I$121,Analysis!$B$2:$B$121,$A15) -> 4170 | C15: =SUMIFS(Analysis!$H$2:$H$121,Analysis!$B$2:$B$121,$A15) -> 5359 | D15: =B15/C15 -> 0.77813025 | E15: =SUMPRODUCT((Analysis!$B$2:$B$121=$A15)*Analysis!$I$2:$I$121*Analysis!$G$2:$G$121) -> 171222.3 | F15: =SUMIFS(Analysis!$W$2:$W$121,Analysis!$B$2:$B$121,$A15) -> 2390 | G15: =SUMIFS(Analysis!$T$2:$T$121,Analysis!$B$2:$B$121,$A15) -> 29960.137 | I15: Tops | J15: =SUMIFS(Analysis!$I$2:$I$121,Analysis!$D$2:$D$121,$I15) -> 3570 | K15: =SUMIFS(Analysis!$I$2:$I$121,Analysis!$D$2:$D$121,$I15)/SUMIFS(Analysis!$H$2:$H$121,Analysis!$D$2:$D$121,$I15) -> 0.82888321 | L15: =SUMIFS(Analysis!$J$2:$J$121,Analysis!$D$2:$D$121,$I15) -> 737 | M15: =SUMIFS(Analysis!$V$2:$V$121,Analysis!$D$2:$D$121,$I15) -> 8
A16: Marketplace Beta | B16: =SUMIFS(Analysis!$I$2:$I$121,Analysis!$B$2:$B$121,$A16) -> 2603 | C16: =SUMIFS(Analysis!$H$2:$H$121,Analysis!$B$2:$B$121,$A16) -> 3342 | D16: =B16/C16 -> 0.77887493 | E16: =SUMPRODUCT((Analysis!$B$2:$B$121=$A16)*Analysis!$I$2:$I$121*Analysis!$G$2:$G$121) -> 106931.97 | F16: =SUMIFS(Analysis!$W$2:$W$121,Analysis!$B$2:$B$121,$A16) -> 1502 | G16: =SUMIFS(Analysis!$T$2:$T$121,Analysis!$B$2:$B$121,$A16) -> 19452.596 | I16: Knitwear | J16: =SUMIFS(Analysis!$I$2:$I$121,Analysis!$D$2:$D$121,$I16) -> 2605 | K16: =SUMIFS(Analysis!$I$2:$I$121,Analysis!$D$2:$D$121,$I16)/SUMIFS(Analysis!$H$2:$H$121,Analysis!$D$2:$D$121,$I16) -> 0.94145284 | L16: =SUMIFS(Analysis!$J$2:$J$121,Analysis!$D$2:$D$121,$I16) -> 162 | M16: =SUMIFS(Analysis!$V$2:$V$121,Analysis!$D$2:$D$121,$I16) -> 0
A17: Marketplace Gamma | B17: =SUMIFS(Analysis!$I$2:$I$121,Analysis!$B$2:$B$121,$A17) -> 3539 | C17: =SUMIFS(Analysis!$H$2:$H$121,Analysis!$B$2:$B$121,$A17) -> 4544 | D17: =B17/C17 -> 0.77882923 | E17: =SUMPRODUCT((Analysis!$B$2:$B$121=$A17)*Analysis!$I$2:$I$121*Analysis!$G$2:$G$121) -> 145431.61 | F17: =SUMIFS(Analysis!$W$2:$W$121,Analysis!$B$2:$B$121,$A17) -> 2120 | G17: =SUMIFS(Analysis!$T$2:$T$121,Analysis!$B$2:$B$121,$A17) -> 26750.715 | I17: Trousers | J17: =SUMIFS(Analysis!$I$2:$I$121,Analysis!$D$2:$D$121,$I17) -> 2272 | K17: =SUMIFS(Analysis!$I$2:$I$121,Analysis!$D$2:$D$121,$I17)/SUMIFS(Analysis!$H$2:$H$121,Analysis!$D$2:$D$121,$I17) -> 0.79803302 | L17: =SUMIFS(Analysis!$J$2:$J$121,Analysis!$D$2:$D$121,$I17) -> 575 | M17: =SUMIFS(Analysis!$V$2:$V$121,Analysis!$D$2:$D$121,$I17) -> 0
I18: Outerwear | J18: =SUMIFS(Analysis!$I$2:$I$121,Analysis!$D$2:$D$121,$I18) -> 1935 | K18: =SUMIFS(Analysis!$I$2:$I$121,Analysis!$D$2:$D$121,$I18)/SUMIFS(Analysis!$H$2:$H$121,Analysis!$D$2:$D$121,$I18) -> 0.53779878 | L18: =SUMIFS(Analysis!$J$2:$J$121,Analysis!$D$2:$D$121,$I18) -> 1663 | M18: =SUMIFS(Analysis!$V$2:$V$121,Analysis!$D$2:$D$121,$I18) -> 12
A35: WEEKLY CUMULATIVE SELL-THROUGH (chart data)
A36: Week | B36: Own Site | C36: Marketplace Alpha | D36: Marketplace Beta | E36: Marketplace Gamma
A37: 1 | B37: =SUMIFS(Fact_Weekly!$E$2:$E$1500,Fact_Weekly!$C$2:$C$1500,B$36,Fact_Weekly!$A$2:$A$1500,"<="&$A37)/$C$14 -> 0.11600297 | C37: =SUMIFS(Fact_Weekly!$E$2:$E$1500,Fact_Weekly!$C$2:$C$1500,C$36,Fact_Weekly!$A$2:$A$1500,"<="&$A37)/$C$15 -> 0.11662624 | D37: =SUMIFS(Fact_Weekly!$E$2:$E$1500,Fact_Weekly!$C$2:$C$1500,D$36,Fact_Weekly!$A$2:$A$1500,"<="&$A37)/$C$16 -> 0.12148414 | E37: =SUMIFS(Fact_Weekly!$E$2:$E$1500,Fact_Weekly!$C$2:$C$1500,E$36,Fact_Weekly!$A$2:$A$1500,"<="&$A37)/$C$17 -> 0.12830106
A38: 2 | B38: =SUMIFS(Fact_Weekly!$E$2:$E$1500,Fact_Weekly!$C$2:$C$1500,B$36,Fact_Weekly!$A$2:$A$1500,"<="&$A38)/$C$14 -> 0.21568142 | C38: =SUMIFS(Fact_Weekly!$E$2:$E$1500,Fact_Weekly!$C$2:$C$1500,C$36,Fact_Weekly!$A$2:$A$1500,"<="&$A38)/$C$15 -> 0.22112334 | D38: =SUMIFS(Fact_Weekly!$E$2:$E$1500,Fact_Weekly!$C$2:$C$1500,D$36,Fact_Weekly!$A$2:$A$1500,"<="&$A38)/$C$16 -> 0.22052663 | E38: =SUMIFS(Fact_Weekly!$E$2:$E$1500,Fact_Weekly!$C$2:$C$1500,E$36,Fact_Weekly!$A$2:$A$1500,"<="&$A38)/$C$17 -> 0.23173415
A39: 3 | B39: =SUMIFS(Fact_Weekly!$E$2:$E$1500,Fact_Weekly!$C$2:$C$1500,B$36,Fact_Weekly!$A$2:$A$1500,"<="&$A39)/$C$14 -> 0.30076676 | C39: =SUMIFS(Fact_Weekly!$E$2:$E$1500,Fact_Weekly!$C$2:$C$1500,C$36,Fact_Weekly!$A$2:$A$1500,"<="&$A39)/$C$15 -> 0.31031909 | D39: =SUMIFS(Fact_Weekly!$E$2:$E$1500,Fact_Weekly!$C$2:$C$1500,D$36,Fact_Weekly!$A$2:$A$1500,"<="&$A39)/$C$16 -> 0.30789946 | E39: =SUMIFS(Fact_Weekly!$E$2:$E$1500,Fact_Weekly!$C$2:$C$1500,E$36,Fact_Weekly!$A$2:$A$1500,"<="&$A39)/$C$17 -> 0.32108275
A40: 4 | B40: =SUMIFS(Fact_Weekly!$E$2:$E$1500,Fact_Weekly!$C$2:$C$1500,B$36,Fact_Weekly!$A$2:$A$1500,"<="&$A40)/$C$14 -> 0.37793718 | C40: =SUMIFS(Fact_Weekly!$E$2:$E$1500,Fact_Weekly!$C$2:$C$1500,C$36,Fact_Weekly!$A$2:$A$1500,"<="&$A40)/$C$15 -> 0.3871991 | D40: =SUMIFS(Fact_Weekly!$E$2:$E$1500,Fact_Weekly!$C$2:$C$1500,D$36,Fact_Weekly!$A$2:$A$1500,"<="&$A40)/$C$16 -> 0.38779174 | E40: =SUMIFS(Fact_Weekly!$E$2:$E$1500,Fact_Weekly!$C$2:$C$1500,E$36,Fact_Weekly!$A$2:$A$1500,"<="&$A40)/$C$17 -> 0.39590669
A41: 5 | B41: =SUMIFS(Fact_Weekly!$E$2:$E$1500,Fact_Weekly!$C$2:$C$1500,B$36,Fact_Weekly!$A$2:$A$1500,"<="&$A41)/$C$14 -> 0.43927776 | C41: =SUMIFS(Fact_Weekly!$E$2:$E$1500,Fact_Weekly!$C$2:$C$1500,C$36,Fact_Weekly!$A$2:$A$1500,"<="&$A41)/$C$15 -> 0.44541892 | D41: =SUMIFS(Fact_Weekly!$E$2:$E$1500,Fact_Weekly!$C$2:$C$1500,D$36,Fact_Weekly!$A$2:$A$1500,"<="&$A41)/$C$16 -> 0.44943148 | E41: =SUMIFS(Fact_Weekly!$E$2:$E$1500,Fact_Weekly!$C$2:$C$1500,E$36,Fact_Weekly!$A$2:$A$1500,"<="&$A41)/$C$17 -> 0.453125
A42: 6 | B42: =SUMIFS(Fact_Weekly!$E$2:$E$1500,Fact_Weekly!$C$2:$C$1500,B$36,Fact_Weekly!$A$2:$A$1500,"<="&$A42)/$C$14 -> 0.49146673 | C42: =SUMIFS(Fact_Weekly!$E$2:$E$1500,Fact_Weekly!$C$2:$C$1500,C$36,Fact_Weekly!$A$2:$A$1500,"<="&$A42)/$C$15 -> 0.49766748 | D42: =SUMIFS(Fact_Weekly!$E$2:$E$1500,Fact_Weekly!$C$2:$C$1500,D$36,Fact_Weekly!$A$2:$A$1500,"<="&$A42)/$C$16 -> 0.50329144 | E42: =SUMIFS(Fact_Weekly!$E$2:$E$1500,Fact_Weekly!$C$2:$C$1500,E$36,Fact_Weekly!$A$2:$A$1500,"<="&$A42)/$C$17 -> 0.50484155
A43: 7 | B43: =SUMIFS(Fact_Weekly!$E$2:$E$1500,Fact_Weekly!$C$2:$C$1500,B$36,Fact_Weekly!$A$2:$A$1500,"<="&$A43)/$C$14 -> 0.54167697 | C43: =SUMIFS(Fact_Weekly!$E$2:$E$1500,Fact_Weekly!$C$2:$C$1500,C$36,Fact_Weekly!$A$2:$A$1500,"<="&$A43)/$C$15 -> 0.54805001 | D43: =SUMIFS(Fact_Weekly!$E$2:$E$1500,Fact_Weekly!$C$2:$C$1500,D$36,Fact_Weekly!$A$2:$A$1500,"<="&$A43)/$C$16 -> 0.55266308 | E43: =SUMIFS(Fact_Weekly!$E$2:$E$1500,Fact_Weekly!$C$2:$C$1500,E$36,Fact_Weekly!$A$2:$A$1500,"<="&$A43)/$C$17 -> 0.55215669
A44: 8 | B44: =SUMIFS(Fact_Weekly!$E$2:$E$1500,Fact_Weekly!$C$2:$C$1500,B$36,Fact_Weekly!$A$2:$A$1500,"<="&$A44)/$C$14 -> 0.58792976 | C44: =SUMIFS(Fact_Weekly!$E$2:$E$1500,Fact_Weekly!$C$2:$C$1500,C$36,Fact_Weekly!$A$2:$A$1500,"<="&$A44)/$C$15 -> 0.59600672 | D44: =SUMIFS(Fact_Weekly!$E$2:$E$1500,Fact_Weekly!$C$2:$C$1500,D$36,Fact_Weekly!$A$2:$A$1500,"<="&$A44)/$C$16 -> 0.60113704 | E44: =SUMIFS(Fact_Weekly!$E$2:$E$1500,Fact_Weekly!$C$2:$C$1500,E$36,Fact_Weekly!$A$2:$A$1500,"<="&$A44)/$C$17 -> 0.59903169
A45: 9 | B45: =SUMIFS(Fact_Weekly!$E$2:$E$1500,Fact_Weekly!$C$2:$C$1500,B$36,Fact_Weekly!$A$2:$A$1500,"<="&$A45)/$C$14 -> 0.63541924 | C45: =SUMIFS(Fact_Weekly!$E$2:$E$1500,Fact_Weekly!$C$2:$C$1500,C$36,Fact_Weekly!$A$2:$A$1500,"<="&$A45)/$C$15 -> 0.64415003 | D45: =SUMIFS(Fact_Weekly!$E$2:$E$1500,Fact_Weekly!$C$2:$C$1500,D$36,Fact_Weekly!$A$2:$A$1500,"<="&$A45)/$C$16 -> 0.64901257 | E45: =SUMIFS(Fact_Weekly!$E$2:$E$1500,Fact_Weekly!$C$2:$C$1500,E$36,Fact_Weekly!$A$2:$A$1500,"<="&$A45)/$C$17 -> 0.64502641
A46: 10 | B46: =SUMIFS(Fact_Weekly!$E$2:$E$1500,Fact_Weekly!$C$2:$C$1500,B$36,Fact_Weekly!$A$2:$A$1500,"<="&$A46)/$C$14 -> 0.68191937 | C46: =SUMIFS(Fact_Weekly!$E$2:$E$1500,Fact_Weekly!$C$2:$C$1500,C$36,Fact_Weekly!$A$2:$A$1500,"<="&$A46)/$C$15 -> 0.69042732 | D46: =SUMIFS(Fact_Weekly!$E$2:$E$1500,Fact_Weekly!$C$2:$C$1500,D$36,Fact_Weekly!$A$2:$A$1500,"<="&$A46)/$C$16 -> 0.6929982 | E46: =SUMIFS(Fact_Weekly!$E$2:$E$1500,Fact_Weekly!$C$2:$C$1500,E$36,Fact_Weekly!$A$2:$A$1500,"<="&$A46)/$C$17 -> 0.69168134
A47: 11 | B47: =SUMIFS(Fact_Weekly!$E$2:$E$1500,Fact_Weekly!$C$2:$C$1500,B$36,Fact_Weekly!$A$2:$A$1500,"<="&$A47)/$C$14 -> 0.72569874 | C47: =SUMIFS(Fact_Weekly!$E$2:$E$1500,Fact_Weekly!$C$2:$C$1500,C$36,Fact_Weekly!$A$2:$A$1500,"<="&$A47)/$C$15 -> 0.7359582 | D47: =SUMIFS(Fact_Weekly!$E$2:$E$1500,Fact_Weekly!$C$2:$C$1500,D$36,Fact_Weekly!$A$2:$A$1500,"<="&$A47)/$C$16 -> 0.73877917 | E47: =SUMIFS(Fact_Weekly!$E$2:$E$1500,Fact_Weekly!$C$2:$C$1500,E$36,Fact_Weekly!$A$2:$A$1500,"<="&$A47)/$C$17 -> 0.73613556
A48: 12 | B48: =SUMIFS(Fact_Weekly!$E$2:$E$1500,Fact_Weekly!$C$2:$C$1500,B$36,Fact_Weekly!$A$2:$A$1500,"<="&$A48)/$C$14 -> 0.76923077 | C48: =SUMIFS(Fact_Weekly!$E$2:$E$1500,Fact_Weekly!$C$2:$C$1500,C$36,Fact_Weekly!$A$2:$A$1500,"<="&$A48)/$C$15 -> 0.77813025 | D48: =SUMIFS(Fact_Weekly!$E$2:$E$1500,Fact_Weekly!$C$2:$C$1500,D$36,Fact_Weekly!$A$2:$A$1500,"<="&$A48)/$C$16 -> 0.77887493 | E48: =SUMIFS(Fact_Weekly!$E$2:$E$1500,Fact_Weekly!$C$2:$C$1500,E$36,Fact_Weekly!$A$2:$A$1500,"<="&$A48)/$C$17 -> 0.77882923

Sheet Actions
A1: Recommended Action | B1: (All)
A3: SKU | B3: Style | C3: Channel | D3: Average of Sell-Through % | E3: Average of Weeks of Cover | F3: Sum of Ending Stock | G3: Sum of Reorder Qty
A4: VS-101-BLA | B4: Ribbed Jersey Top | C4: Marketplace Alpha | D4: 1 | E4: 0 | F4: 0 | G4: 146
A5: VS-101-BLA | B5: Ribbed Jersey Top | C5: Marketplace Beta | D5: 1 | E5: 0 | F5: 0 | G5: 85
A6: VS-101-BLA | B6: Ribbed Jersey Top | C6: Marketplace Gamma | D6: 0.96052632 | E6: 0.57142857 | F6: 9 | G6: 86
A7: VS-101-BLA | B7: Ribbed Jersey Top | C7: Own Site | D7: 1 | E7: 0 | F7: 0 | G7: 108
A8: VS-101-SAN | B8: Ribbed Jersey Top | C8: Marketplace Alpha | D8: 0.86016949 | E8: 1.7368421 | F8: 33 | G8: 81
A9: VS-101-SAN | B9: Ribbed Jersey Top | C9: Marketplace Beta | D9: 0.99295775 | E9: 0.083333333 | F9: 1 | G9: 71
A10: VS-101-SAN | B10: Ribbed Jersey Top | C10: Marketplace Gamma | D10: 0.97382199 | E10: 0.3030303 | F10: 5 | G10: 94
A11: VS-101-SAN | B11: Ribbed Jersey Top | C11: Own Site | D11: 1 | E11: 0 | F11: 0 | G11: 89
A12: VS-101-WHI | B12: Ribbed Jersey Top | C12: Marketplace Alpha | D12: 0.93145161 | E12: 0.8 | F12: 17 | G12: 111
A13: VS-101-WHI | B13: Ribbed Jersey Top | C13: Marketplace Beta | D13: 0.85119048 | E13: 2.0408163 | F13: 25 | G13: 49
A14: VS-101-WHI | B14: Ribbed Jersey Top | C14: Marketplace Gamma | D14: 1 | E14: 0 | F14: 0 | G14: 117
A15: VS-101-WHI | B15: Ribbed Jersey Top | C15: Own Site | D15: 0.93969849 | E15: 0.72727273 | F15: 12 | G15: 87
... A123: VS-303-STO | B123: Belted Trench Coat | C123: Own Site | D123: 0.74137931 | E123: 4.4444444 | F123: 30 | G123: 0
A124: Grand Total | D124: 0.80938489 | E124: 6.4841503 | F124: 3866 | G124: 7672

Sheet Assumptions
A1: Assumptions & Decision Thresholds
A2: Edit the yellow cells — the whole model re-decides.
A4: Parameter | B4: Value | C4: Notes
A5: Target sell-through (reorder trigger) | B5: 0.8 | C5: At/above this, demand is proven — replenish.
A6: Markdown sell-through ceiling | B6: 0.6 | C6: Seasonal style below this + overstocked = clear.
A7: Reorder weeks-of-cover threshold | B7: 3 | C7: Core stock below this many weeks = replenish.
A8: Overstock weeks-of-cover threshold | B8: 8 | C8: Above this + weak sell-through = markdown.
A9: Target weeks of cover (reorder sizing) | B9: 6 | C9: Reorder rebuilds stock to this many weeks.
A10: Lead time (weeks) | B10: 2 | C10: Supplier/marketplace replenishment lead time.
A11: Recent window for velocity (weeks) | B11: 4 | C11: Weeks used to measure current selling speed.
A12: Season length (weeks) | B12: 12 | C12: Length of the selling period in the dataset.

Sheet Dim_Product
A1: SKU | B1: Style | C1: StyleID | D1: Category | E1: Colour | F1: NOOS_Flag | G1: List_Price
A2: VS-101-BLA | B2: Ribbed Jersey Top | C2: VS-101 | D2: Tops | E2: Black | F2: Core | G2: 17.99
A3: VS-101-WHI | B3: Ribbed Jersey Top | C3: VS-101 | D3: Tops | E3: White | F3: Core | G3: 17.99
A4: VS-101-SAN | B4: Ribbed Jersey Top | C4: VS-101 | D4: Tops | E4: Sand | F4: Core | G4: 17.99
A5: VS-102-ECR | B5: Fine-Knit Cardigan | C5: VS-102 | D5: Knitwear | E5: Ecru | F5: Core | G5: 39.99
A6: VS-102-NAV | B6: Fine-Knit Cardigan | C6: VS-102 | D6: Knitwear | E6: Navy | F6: Core | G6: 39.99
A7: VS-102-GRE | B7: Fine-Knit Cardigan | C7: VS-102 | D7: Knitwear | E7: Grey | F7: Core | G7: 39.99
A8: VS-103-BLA | B8: Tailored Cigarette Trouser | C8: VS-103 | D8: Trousers | E8: Black | F8: Core | G8: 44.99
A9: VS-103-CAM | B9: Tailored Cigarette Trouser | C9: VS-103 | D9: Trousers | E9: Camel | F9: Core | G9: 44.99
A10: VS-104-BLA | B10: Roll-Neck Jumper | C10: VS-104 | D10: Knitwear | E10: Black | F10: Core | G10: 34.99
A11: VS-104-CRE | B11: Roll-Neck Jumper | C11: VS-104 | D11: Knitwear | E11: Cream | F11: Core | G11: 34.99
A12: VS-104-RUS | B12: Roll-Neck Jumper | C12: VS-104 | D12: Knitwear | E12: Rust | F12: Core | G12: 34.99
A13: VS-201-BLU | B13: Floral Midi Dress | C13: VS-201 | D13: Dresses | E13: Blue Floral | F13: Seasonal | G13: 49.99
... A31: VS-303-KHA | B31: Belted Trench Coat | C31: VS-303 | D31: Outerwear | E31: Khaki | F31: Seasonal | G31: 79.99

Sheet Fact_Weekly
A1: Week | B1: SKU | C1: Channel | D1: Units_Received | E1: Units_Sold | F1: Opening_Stock | G1: Closing_Stock
A2: 1 | B2: VS-101-BLA | C2: Own Site | D2: 198 | E2: 19 | F2: =IF(A2=1,0,G1) -> 0 | G2: =F2+D2-E2 -> 179
A3: 2 | B3: VS-101-BLA | C3: Own Site | D3: 0 | E3: 18 | F3: =IF(A3=1,0,G2) -> 179 | G3: =F3+D3-E3 -> 161
A4: 3 | B4: VS-101-BLA | C4: Own Site | D4: 0 | E4: 12 | F4: =IF(A4=1,0,G3) -> 161 | G4: =F4+D4-E4 -> 149
A5: 4 | B5: VS-101-BLA | C5: Own Site | D5: 0 | E5: 20 | F5: =IF(A5=1,0,G4) -> 149 | G5: =F5+D5-E5 -> 129
A6: 5 | B6: VS-101-BLA | C6: Own Site | D6: 0 | E6: 18 | F6: =IF(A6=1,0,G5) -> 129 | G6: =F6+D6-E6 -> 111
A7: 6 | B7: VS-101-BLA | C7: Own Site | D7: 0 | E7: 19 | F7: =IF(A7=1,0,G6) -> 111 | G7: =F7+D7-E7 -> 92
A8: 7 | B8: VS-101-BLA | C8: Own Site | D8: 0 | E8: 12 | F8: =IF(A8=1,0,G7) -> 92 | G8: =F8+D8-E8 -> 80
A9: 8 | B9: VS-101-BLA | C9: Own Site | D9: 0 | E9: 15 | F9: =IF(A9=1,0,G8) -> 80 | G9: =F9+D9-E9 -> 65
A10: 9 | B10: VS-101-BLA | C10: Own Site | D10: 0 | E10: 15 | F10: =IF(A10=1,0,G9) -> 65 | G10: =F10+D10-E10 -> 50
A11: 10 | B11: VS-101-BLA | C11: Own Site | D11: 0 | E11: 20 | F11: =IF(A11=1,0,G10) -> 50 | G11: =F11+D11-E11 -> 30
A12: 11 | B12: VS-101-BLA | C12: Own Site | D12: 0 | E12: 17 | F12: =IF(A12=1,0,G11) -> 30 | G12: =F12+D12-E12 -> 13
A13: 12 | B13: VS-101-BLA | C13: Own Site | D13: 0 | E13: 13 | F13: =IF(A13=1,0,G12) -> 13 | G13: =F13+D13-E13 -> 0
... A1441: 12 | B1441: VS-303-KHA | C1441: Marketplace Gamma | D1441: 0 | E1441: 10 | F1441: =IF(A1441=1,0,G1440) -> 47 | G1441: =F1441+D1441-E1441 -> 37

Sheet Analysis
A1: SKU | B1: Channel | C1: Style | D1: Category | E1: Colour | F1: NOOS | G1: List Price | H1: Units Received | I1: Units Sold | J1: Ending Stock | K1: Sell-Through % | L1: Recent (last 4 weeks)Sales | M1: Avg per Wk (recent) | N1: Weeks Selling | O1: Avg per Wk (live) | P1: Weeks of Cover | Q1: Stock-out? | R1: Velocity | S1: Missed Units (planned rate) | T1: Missed Rev € | U1: Reorder? | V1: Markdown? | W1: Reorder Qty | X1: Recommended Action
A2: VS-101-BLA | B2: Own Site | C2: =INDEX(Dim_Product!$B:B, MATCH($A2,Dim_Product!$A:$A,0)) -> Ribbed Jersey Top | D2: =INDEX(Dim_Product!$D:D, MATCH($A2,Dim_Product!$A:$A,0)) -> Tops | E2: =INDEX(Dim_Product!$E:E, MATCH($A2,Dim_Product!$A:$A,0)) -> Black | F2: =INDEX(Dim_Product!$F:F, MATCH($A2,Dim_Product!$A:$A,0)) -> Core | G2: =INDEX(Dim_Product!$G:G, MATCH($A2,Dim_Product!$A:$A,0)) -> 17.99 | H2: =SUMIFS(Fact_Weekly!$D$2:$D$1500,Fact_Weekly!$B$2:$B$1500,$A2,Fact_Weekly!$C$2:$C$1500,$B2) -> 198 | I2: =SUMIFS(Fact_Weekly!$E$2:$E$1500,Fact_Weekly!$B$2:$B$1500,$A2,Fact_Weekly!$C$2:$C$1500,$B2) -> 198 | J2: =H2-I2 -> 0 | K2: =IF(H2>0,I2/H2,0) -> 1 | L2: =SUMIFS(Fact_Weekly!$E$2:$E$1500,Fact_Weekly!$B$2:$B$1500,$A2,Fact_Weekly!$C$2:$C$1500,$B2,Fact_Weekly!$A$2:$A$1500,">="&(Assumptions!$B$12-Assumptions!$B$11+1)) -> 65 | M2: =L2/Assumptions!$B$11 -> 16.25 | N2: =COUNTIFS(Fact_Weekly!$B$2:$B$1500,$A2,Fact_Weekly!$C$2:$C$1500,$B2,Fact_Weekly!$G$2:$G$1500,">0") -> 11 | O2: =IF(N2>0,I2/N2,0) -> 18 | P2: =IF(M2>0,J2/M2,IF(J2>0,Assumptions!$B$12,0)) -> 0 | Q2: =IF(AND(N2<Assumptions!$B$12,K2>=0.99),1,0) -> 1 | R2: =IF(Q2=1,O2,M2) -> 18 | S2: =IF(Q2=1,(Assumptions!$B$12-N2)*(H2/Assumptions!$B$12),0) -> 16.5 | T2: =S2*G2 -> 296.835 | U2: =IF(OR(K2>=Assumptions!$B$5,Q2=1,AND(F2="Core",P2<Assumptions!$B$7)),1,0) -> 1 | V2: =IF(AND(F2="Seasonal",K2<Assumptions!$B$6,P2>Assumptions!$B$8),1,0) -> 0 | W2: =IF(U2=1,ROUND(MAX(0,Assumptions!$B$9*R2-J2),0),0) -> 108 | X2: =IF(V2=1,"Markdown / clear",IF(AND(U2=1,Q2=1),"Reorder - recover lost sales",IF(U2=1,"Reorder / replenish","Maintain / monitor"))) -> Reorder - recover lost sales
A3: VS-101-BLA | B3: Marketplace Alpha | C3: =INDEX(Dim_Product!$B:B, MATCH($A3,Dim_Product!$A:$A,0)) -> Ribbed Jersey Top | D3: =INDEX(Dim_Product!$D:D, MATCH($A3,Dim_Product!$A:$A,0)) -> Tops | E3: =INDEX(Dim_Product!$E:E, MATCH($A3,Dim_Product!$A:$A,0)) -> Black | F3: =INDEX(Dim_Product!$F:F, MATCH($A3,Dim_Product!$A:$A,0)) -> Core | G3: =INDEX(Dim_Product!$G:G, MATCH($A3,Dim_Product!$A:$A,0)) -> 17.99 | H3: =SUMIFS(Fact_Weekly!$D$2:$D$1500,Fact_Weekly!$B$2:$B$1500,$A3,Fact_Weekly!$C$2:$C$1500,$B3) -> 268 | I3: =SUMIFS(Fact_Weekly!$E$2:$E$1500,Fact_Weekly!$B$2:$B$1500,$A3,Fact_Weekly!$C$2:$C$1500,$B3) -> 268 | J3: =H3-I3 -> 0 | K3: =IF(H3>0,I3/H3,0) -> 1 | L3: =SUMIFS(Fact_Weekly!$E$2:$E$1500,Fact_Weekly!$B$2:$B$1500,$A3,Fact_Weekly!$C$2:$C$1500,$B3,Fact_Weekly!$A$2:$A$1500,">="&(Assumptions!$B$12-Assumptions!$B$11+1)) -> 90 | M3: =L3/Assumptions!$B$11 -> 22.5 | N3: =COUNTIFS(Fact_Weekly!$B$2:$B$1500,$A3,Fact_Weekly!$C$2:$C$1500,$B3,Fact_Weekly!$G$2:$G$1500,">0") -> 11 | O3: =IF(N3>0,I3/N3,0) -> 24.363636 | P3: =IF(M3>0,J3/M3,IF(J3>0,Assumptions!$B$12,0)) -> 0 | Q3: =IF(AND(N3<Assumptions!$B$12,K3>=0.99),1,0) -> 1 | R3: =IF(Q3=1,O3,M3) -> 24.363636 | S3: =IF(Q3=1,(Assumptions!$B$12-N3)*(H3/Assumptions!$B$12),0) -> 22.333333 | T3: =S3*G3 -> 401.77667 | U3: =IF(OR(K3>=Assumptions!$B$5,Q3=1,AND(F3="Core",P3<Assumptions!$B$7)),1,0) -> 1 | V3: =IF(AND(F3="Seasonal",K3<Assumptions!$B$6,P3>Assumptions!$B$8),1,0) -> 0 | W3: =IF(U3=1,ROUND(MAX(0,Assumptions!$B$9*R3-J3),0),0) -> 146 | X3: =IF(V3=1,"Markdown / clear",IF(AND(U3=1,Q3=1),"Reorder - recover lost sales",IF(U3=1,"Reorder / replenish","Maintain / monitor"))) -> Reorder - recover lost sales
A4: VS-101-BLA | B4: Marketplace Beta | C4: =INDEX(Dim_Product!$B:B, MATCH($A4,Dim_Product!$A:$A,0)) -> Ribbed Jersey Top | D4: =INDEX(Dim_Product!$D:D, MATCH($A4,Dim_Product!$A:$A,0)) -> Tops | E4: =INDEX(Dim_Product!$E:E, MATCH($A4,Dim_Product!$A:$A,0)) -> Black | F4: =INDEX(Dim_Product!$F:F, MATCH($A4,Dim_Product!$A:$A,0)) -> Core | G4: =INDEX(Dim_Product!$G:G, MATCH($A4,Dim_Product!$A:$A,0)) -> 17.99 | H4: =SUMIFS(Fact_Weekly!$D$2:$D$1500,Fact_Weekly!$B$2:$B$1500,$A4,Fact_Weekly!$C$2:$C$1500,$B4) -> 155 | I4: =SUMIFS(Fact_Weekly!$E$2:$E$1500,Fact_Weekly!$B$2:$B$1500,$A4,Fact_Weekly!$C$2:$C$1500,$B4) -> 155 | J4: =H4-I4 -> 0 | K4: =IF(H4>0,I4/H4,0) -> 1 | L4: =SUMIFS(Fact_Weekly!$E$2:$E$1500,Fact_Weekly!$B$2:$B$1500,$A4,Fact_Weekly!$C$2:$C$1500,$B4,Fact_Weekly!$A$2:$A$1500,">="&(Assumptions!$B$12-Assumptions!$B$11+1)) -> 48 | M4: =L4/Assumptions!$B$11 -> 12 | N4: =COUNTIFS(Fact_Weekly!$B$2:$B$1500,$A4,Fact_Weekly!$C$2:$C$1500,$B4,Fact_Weekly!$G$2:$G$1500,">0") -> 11 | O4: =IF(N4>0,I4/N4,0) -> 14.090909 | P4: =IF(M4>0,J4/M4,IF(J4>0,Assumptions!$B$12,0)) -> 0 | Q4: =IF(AND(N4<Assumptions!$B$12,K4>=0.99),1,0) -> 1 | R4: =IF(Q4=1,O4,M4) -> 14.090909 | S4: =IF(Q4=1,(Assumptions!$B$12-N4)*(H4/Assumptions!$B$12),0) -> 12.916667 | T4: =S4*G4 -> 232.37083 | U4: =IF(OR(K4>=Assumptions!$B$5,Q4=1,AND(F4="Core",P4<Assumptions!$B$7)),1,0) -> 1 | V4: =IF(AND(F4="Seasonal",K4<Assumptions!$B$6,P4>Assumptions!$B$8),1,0) -> 0 | W4: =IF(U4=1,ROUND(MAX(0,Assumptions!$B$9*R4-J4),0),0) -> 85 | X4: =IF(V4=1,"Markdown / clear",IF(AND(U4=1,Q4=1),"Reorder - recover lost sales",IF(U4=1,"Reorder / replenish","Maintain / monitor"))) -> Reorder - recover lost sales
A5: VS-101-BLA | B5: Marketplace Gamma | C5: =INDEX(Dim_Product!$B:B, MATCH($A5,Dim_Product!$A:$A,0)) -> Ribbed Jersey Top | D5: =INDEX(Dim_Product!$D:D, MATCH($A5,Dim_Product!$A:$A,0)) -> Tops | E5: =INDEX(Dim_Product!$E:E, MATCH($A5,Dim_Product!$A:$A,0)) -> Black | F5: =INDEX(Dim_Product!$F:F, MATCH($A5,Dim_Product!$A:$A,0)) -> Core | G5: =INDEX(Dim_Product!$G:G, MATCH($A5,Dim_Product!$A:$A,0)) -> 17.99 | H5: =SUMIFS(Fact_Weekly!$D$2:$D$1500,Fact_Weekly!$B$2:$B$1500,$A5,Fact_Weekly!$C$2:$C$1500,$B5) -> 228 | I5: =SUMIFS(Fact_Weekly!$E$2:$E$1500,Fact_Weekly!$B$2:$B$1500,$A5,Fact_Weekly!$C$2:$C$1500,$B5) -> 219 | J5: =H5-I5 -> 9 | K5: =IF(H5>0,I5/H5,0) -> 0.96052632 | L5: =SUMIFS(Fact_Weekly!$E$2:$E$1500,Fact_Weekly!$B$2:$B$1500,$A5,Fact_Weekly!$C$2:$C$1500,$B5,Fact_Weekly!$A$2:$A$1500,">="&(Assumptions!$B$12-Assumptions!$B$11+1)) -> 63 | M5: =L5/Assumptions!$B$11 -> 15.75 | N5: =COUNTIFS(Fact_Weekly!$B$2:$B$1500,$A5,Fact_Weekly!$C$2:$C$1500,$B5,Fact_Weekly!$G$2:$G$1500,">0") -> 12 | O5: =IF(N5>0,I5/N5,0) -> 18.25 | P5: =IF(M5>0,J5/M5,IF(J5>0,Assumptions!$B$12,0)) -> 0.57142857 | Q5: =IF(AND(N5<Assumptions!$B$12,K5>=0.99),1,0) -> 0 | R5: =IF(Q5=1,O5,M5) -> 15.75 | S5: =IF(Q5=1,(Assumptions!$B$12-N5)*(H5/Assumptions!$B$12),0) -> 0 | T5: =S5*G5 -> 0 | U5: =IF(OR(K5>=Assumptions!$B$5,Q5=1,AND(F5="Core",P5<Assumptions!$B$7)),1,0) -> 1 | V5: =IF(AND(F5="Seasonal",K5<Assumptions!$B$6,P5>Assumptions!$B$8),1,0) -> 0 | W5: =IF(U5=1,ROUND(MAX(0,Assumptions!$B$9*R5-J5),0),0) -> 86 | X5: =IF(V5=1,"Markdown / clear",IF(AND(U5=1,Q5=1),"Reorder - recover lost sales",IF(U5=1,"Reorder / replenish","Maintain / monitor"))) -> Reorder / replenish
A6: VS-101-WHI | B6: Own Site | C6: =INDEX(Dim_Product!$B:B, MATCH($A6,Dim_Product!$A:$A,0)) -> Ribbed Jersey Top | D6: =INDEX(Dim_Product!$D:D, MATCH($A6,Dim_Product!$A:$A,0)) -> Tops | E6: =INDEX(Dim_Product!$E:E, MATCH($A6,Dim_Product!$A:$A,0)) -> White | F6: =INDEX(Dim_Product!$F:F, MATCH($A6,Dim_Product!$A:$A,0)) -> Core | G6: =INDEX(Dim_Product!$G:G, MATCH($A6,Dim_Product!$A:$A,0)) -> 17.99 | H6: =SUMIFS(Fact_Weekly!$D$2:$D$1500,Fact_Weekly!$B$2:$B$1500,$A6,Fact_Weekly!$C$2:$C$1500,$B6) -> 199 | I6: =SUMIFS(Fact_Weekly!$E$2:$E$1500,Fact_Weekly!$B$2:$B$1500,$A6,Fact_Weekly!$C$2:$C$1500,$B6) -> 187 | J6: =H6-I6 -> 12 | K6: =IF(H6>0,I6/H6,0) -> 0.93969849 | L6: =SUMIFS(Fact_Weekly!$E$2:$E$1500,Fact_Weekly!$B$2:$B$1500,$A6,Fact_Weekly!$C$2:$C$1500,$B6,Fact_Weekly!$A$2:$A$1500,">="&(Assumptions!$B$12-Assumptions!$B$11+1)) -> 66 | M6: =L6/Assumptions!$B$11 -> 16.5 | N6: =COUNTIFS(Fact_Weekly!$B$2:$B$1500,$A6,Fact_Weekly!$C$2:$C$1500,$B6,Fact_Weekly!$G$2:$G$1500,">0") -> 12 | O6: =IF(N6>0,I6/N6,0) -> 15.583333 | P6: =IF(M6>0,J6/M6,IF(J6>0,Assumptions!$B$12,0)) -> 0.72727273 | Q6: =IF(AND(N6<Assumptions!$B$12,K6>=0.99),1,0) -> 0 | R6: =IF(Q6=1,O6,M6) -> 16.5 | S6: =IF(Q6=1,(Assumptions!$B$12-N6)*(H6/Assumptions!$B$12),0) -> 0 | T6: =S6*G6 -> 0 | U6: =IF(OR(K6>=Assumptions!$B$5,Q6=1,AND(F6="Core",P6<Assumptions!$B$7)),1,0) -> 1 | V6: =IF(AND(F6="Seasonal",K6<Assumptions!$B$6,P6>Assumptions!$B$8),1,0) -> 0 | W6: =IF(U6=1,ROUND(MAX(0,Assumptions!$B$9*R6-J6),0),0) -> 87 | X6: =IF(V6=1,"Markdown / clear",IF(AND(U6=1,Q6=1),"Reorder - recover lost sales",IF(U6=1,"Reorder / replenish","Maintain / monitor"))) -> Reorder / replenish
A7: VS-101-WHI | B7: Marketplace Alpha | C7: =INDEX(Dim_Product!$B:B, MATCH($A7,Dim_Product!$A:$A,0)) -> Ribbed Jersey Top | D7: =INDEX(Dim_Product!$D:D, MATCH($A7,Dim_Product!$A:$A,0)) -> Tops | E7: =INDEX(Dim_Product!$E:E, MATCH($A7,Dim_Product!$A:$A,0)) -> White | F7: =INDEX(Dim_Product!$F:F, MATCH($A7,Dim_Product!$A:$A,0)) -> Core | G7: =INDEX(Dim_Product!$G:G, MATCH($A7,Dim_Product!$A:$A,0)) -> 17.99 | H7: =SUMIFS(Fact_Weekly!$D$2:$D$1500,Fact_Weekly!$B$2:$B$1500,$A7,Fact_Weekly!$C$2:$C$1500,$B7) -> 248 | I7: =SUMIFS(Fact_Weekly!$E$2:$E$1500,Fact_Weekly!$B$2:$B$1500,$A7,Fact_Weekly!$C$2:$C$1500,$B7) -> 231 | J7: =H7-I7 -> 17 | K7: =IF(H7>0,I7/H7,0) -> 0.93145161 | L7: =SUMIFS(Fact_Weekly!$E$2:$E$1500,Fact_Weekly!$B$2:$B$1500,$A7,Fact_Weekly!$C$2:$C$1500,$B7,Fact_Weekly!$A$2:$A$1500,">="&(Assumptions!$B$12-Assumptions!$B$11+1)) -> 85 | M7: =L7/Assumptions!$B$11 -> 21.25 | N7: =COUNTIFS(Fact_Weekly!$B$2:$B$1500,$A7,Fact_Weekly!$C$2:$C$1500,$B7,Fact_Weekly!$G$2:$G$1500,">0") -> 12 | O7: =IF(N7>0,I7/N7,0) -> 19.25 | P7: =IF(M7>0,J7/M7,IF(J7>0,Assumptions!$B$12,0)) -> 0.8 | Q7: =IF(AND(N7<Assumptions!$B$12,K7>=0.99),1,0) -> 0 | R7: =IF(Q7=1,O7,M7) -> 21.25 | S7: =IF(Q7=1,(Assumptions!$B$12-N7)*(H7/Assumptions!$B$12),0) -> 0 | T7: =S7*G7 -> 0 | U7: =IF(OR(K7>=Assumptions!$B$5,Q7=1,AND(F7="Core",P7<Assumptions!$B$7)),1,0) -> 1 | V7: =IF(AND(F7="Seasonal",K7<Assumptions!$B$6,P7>Assumptions!$B$8),1,0) -> 0 | W7: =IF(U7=1,ROUND(MAX(0,Assumptions!$B$9*R7-J7),0),0) -> 111 | X7: =IF(V7=1,"Markdown / clear",IF(AND(U7=1,Q7=1),"Reorder - recover lost sales",IF(U7=1,"Reorder / replenish","Maintain / monitor"))) -> Reorder / replenish
A8: VS-101-WHI | B8: Marketplace Beta | C8: =INDEX(Dim_Product!$B:B, MATCH($A8,Dim_Product!$A:$A,0)) -> Ribbed Jersey Top | D8: =INDEX(Dim_Product!$D:D, MATCH($A8,Dim_Product!$A:$A,0)) -> Tops | E8: =INDEX(Dim_Product!$E:E, MATCH($A8,Dim_Product!$A:$A,0)) -> White | F8: =INDEX(Dim_Product!$F:F, MATCH($A8,Dim_Product!$A:$A,0)) -> Core | G8: =INDEX(Dim_Product!$G:G, MATCH($A8,Dim_Product!$A:$A,0)) -> 17.99 | H8: =SUMIFS(Fact_Weekly!$D$2:$D$1500,Fact_Weekly!$B$2:$B$1500,$A8,Fact_Weekly!$C$2:$C$1500,$B8) -> 168 | I8: =SUMIFS(Fact_Weekly!$E$2:$E$1500,Fact_Weekly!$B$2:$B$1500,$A8,Fact_Weekly!$C$2:$C$1500,$B8) -> 143 | J8: =H8-I8 -> 25 | K8: =IF(H8>0,I8/H8,0) -> 0.85119048 | L8: =SUMIFS(Fact_Weekly!$E$2:$E$1500,Fact_Weekly!$B$2:$B$1500,$A8,Fact_Weekly!$C$2:$C$1500,$B8,Fact_Weekly!$A$2:$A$1500,">="&(Assumptions!$B$12-Assumptions!$B$11+1)) -> 49 | M8: =L8/Assumptions!$B$11 -> 12.25 | N8: =COUNTIFS(Fact_Weekly!$B$2:$B$1500,$A8,Fact_Weekly!$C$2:$C$1500,$B8,Fact_Weekly!$G$2:$G$1500,">0") -> 12 | O8: =IF(N8>0,I8/N8,0) -> 11.916667 | P8: =IF(M8>0,J8/M8,IF(J8>0,Assumptions!$B$12,0)) -> 2.0408163 | Q8: =IF(AND(N8<Assumptions!$B$12,K8>=0.99),1,0) -> 0 | R8: =IF(Q8=1,O8,M8) -> 12.25 | S8: =IF(Q8=1,(Assumptions!$B$12-N8)*(H8/Assumptions!$B$12),0) -> 0 | T8: =S8*G8 -> 0 | U8: =IF(OR(K8>=Assumptions!$B$5,Q8=1,AND(F8="Core",P8<Assumptions!$B$7)),1,0) -> 1 | V8: =IF(AND(F8="Seasonal",K8<Assumptions!$B$6,P8>Assumptions!$B$8),1,0) -> 0 | W8: =IF(U8=1,ROUND(MAX(0,Assumptions!$B$9*R8-J8),0),0) -> 49 | X8: =IF(V8=1,"Markdown / clear",IF(AND(U8=1,Q8=1),"Reorder - recover lost sales",IF(U8=1,"Reorder / replenish","Maintain / monitor"))) -> Reorder / replenish
A9: VS-101-WHI | B9: Marketplace Gamma | C9: =INDEX(Dim_Product!$B:B, MATCH($A9,Dim_Product!$A:$A,0)) -> Ribbed Jersey Top | D9: =INDEX(Dim_Product!$D:D, MATCH($A9,Dim_Product!$A:$A,0)) -> Tops | E9: =INDEX(Dim_Product!$E:E, MATCH($A9,Dim_Product!$A:$A,0)) -> White | F9: =INDEX(Dim_Product!$F:F, MATCH($A9,Dim_Product!$A:$A,0)) -> Core | G9: =INDEX(Dim_Product!$G:G, MATCH($A9,Dim_Product!$A:$A,0)) -> 17.99 | H9: =SUMIFS(Fact_Weekly!$D$2:$D$1500,Fact_Weekly!$B$2:$B$1500,$A9,Fact_Weekly!$C$2:$C$1500,$B9) -> 214 | I9: =SUMIFS(Fact_Weekly!$E$2:$E$1500,Fact_Weekly!$B$2:$B$1500,$A9,Fact_Weekly!$C$2:$C$1500,$B9) -> 214 | J9: =H9-I9 -> 0 | K9: =IF(H9>0,I9/H9,0) -> 1 | L9: =SUMIFS(Fact_Weekly!$E$2:$E$1500,Fact_Weekly!$B$2:$B$1500,$A9,Fact_Weekly!$C$2:$C$1500,$B9,Fact_Weekly!$A$2:$A$1500,">="&(Assumptions!$B$12-Assumptions!$B$11+1)) -> 74 | M9: =L9/Assumptions!$B$11 -> 18.5 | N9: =COUNTIFS(Fact_Weekly!$B$2:$B$1500,$A9,Fact_Weekly!$C$2:$C$1500,$B9,Fact_Weekly!$G$2:$G$1500,">0") -> 11 | O9: =IF(N9>0,I9/N9,0) -> 19.454545 | P9: =IF(M9>0,J9/M9,IF(J9>0,Assumptions!$B$12,0)) -> 0 | Q9: =IF(AND(N9<Assumptions!$B$12,K9>=0.99),1,0) -> 1 | R9: =IF(Q9=1,O9,M9) -> 19.454545 | S9: =IF(Q9=1,(Assumptions!$B$12-N9)*(H9/Assumptions!$B$12),0) -> 17.833333 | T9: =S9*G9 -> 320.82167 | U9: =IF(OR(K9>=Assumptions!$B$5,Q9=1,AND(F9="Core",P9<Assumptions!$B$7)),1,0) -> 1 | V9: =IF(AND(F9="Seasonal",K9<Assumptions!$B$6,P9>Assumptions!$B$8),1,0) -> 0 | W9: =IF(U9=1,ROUND(MAX(0,Assumptions!$B$9*R9-J9),0),0) -> 117 | X9: =IF(V9=1,"Markdown / clear",IF(AND(U9=1,Q9=1),"Reorder - recover lost sales",IF(U9=1,"Reorder / replenish","Maintain / monitor"))) -> Reorder - recover lost sales
A10: VS-101-SAN | B10: Own Site | C10: =INDEX(Dim_Product!$B:B, MATCH($A10,Dim_Product!$A:$A,0)) -> Ribbed Jersey Top | D10: =INDEX(Dim_Product!$D:D, MATCH($A10,Dim_Product!$A:$A,0)) -> Tops | E10: =INDEX(Dim_Product!$E:E, MATCH($A10,Dim_Product!$A:$A,0)) -> Sand | F10: =INDEX(Dim_Product!$F:F, MATCH($A10,Dim_Product!$A:$A,0)) -> Core | G10: =INDEX(Dim_Product!$G:G, MATCH($A10,Dim_Product!$A:$A,0)) -> 17.99 | H10: =SUMIFS(Fact_Weekly!$D$2:$D$1500,Fact_Weekly!$B$2:$B$1500,$A10,Fact_Weekly!$C$2:$C$1500,$B10) -> 164 | I10: =SUMIFS(Fact_Weekly!$E$2:$E$1500,Fact_Weekly!$B$2:$B$1500,$A10,Fact_Weekly!$C$2:$C$1500,$B10) -> 164 | J10: =H10-I10 -> 0 | K10: =IF(H10>0,I10/H10,0) -> 1 | L10: =SUMIFS(Fact_Weekly!$E$2:$E$1500,Fact_Weekly!$B$2:$B$1500,$A10,Fact_Weekly!$C$2:$C$1500,$B10,Fact_Weekly!$A$2:$A$1500,">="&(Assumptions!$B$12-Assumptions!$B$11+1)) -> 59 | M10: =L10/Assumptions!$B$11 -> 14.75 | N10: =COUNTIFS(Fact_Weekly!$B$2:$B$1500,$A10,Fact_Weekly!$C$2:$C$1500,$B10,Fact_Weekly!$G$2:$G$1500,">0") -> 11 | O10: =IF(N10>0,I10/N10,0) -> 14.909091 | P10: =IF(M10>0,J10/M10,IF(J10>0,Assumptions!$B$12,0)) -> 0 | Q10: =IF(AND(N10<Assumptions!$B$12,K10>=0.99),1,0) -> 1 | R10: =IF(Q10=1,O10,M10) -> 14.909091 | S10: =IF(Q10=1,(Assumptions!$B$12-N10)*(H10/Assumptions!$B$12),0) -> 13.666667 | T10: =S10*G10 -> 245.86333 | U10: =IF(OR(K10>=Assumptions!$B$5,Q10=1,AND(F10="Core",P10<Assumptions!$B$7)),1,0) -> 1 | V10: =IF(AND(F10="Seasonal",K10<Assumptions!$B$6,P10>Assumptions!$B$8),1,0) -> 0 | W10: =IF(U10=1,ROUND(MAX(0,Assumptions!$B$9*R10-J10),0),0) -> 89 | X10: =IF(V10=1,"Markdown / clear",IF(AND(U10=1,Q10=1),"Reorder - recover lost sales",IF(U10=1,"Reorder / replenish","Maintain / monitor"))) -> Reorder - recover lost sales
A11: VS-101-SAN | B11: Marketplace Alpha | C11: =INDEX(Dim_Product!$B:B, MATCH($A11,Dim_Product!$A:$A,0)) -> Ribbed Jersey Top | D11: =INDEX(Dim_Product!$D:D, MATCH($A11,Dim_Product!$A:$A,0)) -> Tops | E11: =INDEX(Dim_Product!$E:E, MATCH($A11,Dim_Product!$A:$A,0)) -> Sand | F11: =INDEX(Dim_Product!$F:F, MATCH($A11,Dim_Product!$A:$A,0)) -> Core | G11: =INDEX(Dim_Product!$G:G, MATCH($A11,Dim_Product!$A:$A,0)) -> 17.99 | H11: =SUMIFS(Fact_Weekly!$D$2:$D$1500,Fact_Weekly!$B$2:$B$1500,$A11,Fact_Weekly!$C$2:$C$1500,$B11) -> 236 | I11: =SUMIFS(Fact_Weekly!$E$2:$E$1500,Fact_Weekly!$B$2:$B$1500,$A11,Fact_Weekly!$C$2:$C$1500,$B11) -> 203 | J11: =H11-I11 -> 33 | K11: =IF(H11>0,I11/H11,0) -> 0.86016949 | L11: =SUMIFS(Fact_Weekly!$E$2:$E$1500,Fact_Weekly!$B$2:$B$1500,$A11,Fact_Weekly!$C$2:$C$1500,$B11,Fact_Weekly!$A$2:$A$1500,">="&(Assumptions!$B$12-Assumptions!$B$11+1)) -> 76 | M11: =L11/Assumptions!$B$11 -> 19 | N11: =COUNTIFS(Fact_Weekly!$B$2:$B$1500,$A11,Fact_Weekly!$C$2:$C$1500,$B11,Fact_Weekly!$G$2:$G$1500,">0") -> 12 | O11: =IF(N11>0,I11/N11,0) -> 16.916667 | P11: =IF(M11>0,J11/M11,IF(J11>0,Assumptions!$B$12,0)) -> 1.7368421 | Q11: =IF(AND(N11<Assumptions!$B$12,K11>=0.99),1,0) -> 0 | R11: =IF(Q11=1,O11,M11) -> 19 | S11: =IF(Q11=1,(Assumptions!$B$12-N11)*(H11/Assumptions!$B$12),0) -> 0 | T11: =S11*G11 -> 0 | U11: =IF(OR(K11>=Assumptions!$B$5,Q11=1,AND(F11="Core",P11<Assumptions!$B$7)),1,0) -> 1 | V11: =IF(AND(F11="Seasonal",K11<Assumptions!$B$6,P11>Assumptions!$B$8),1,0) -> 0 | W11: =IF(U11=1,ROUND(MAX(0,Assumptions!$B$9*R11-J11),0),0) -> 81 | X11: =IF(V11=1,"Markdown / clear",IF(AND(U11=1,Q11=1),"Reorder - recover lost sales",IF(U11=1,"Reorder / replenish","Maintain / monitor"))) -> Reorder / replenish
A12: VS-101-SAN | B12: Marketplace Beta | C12: =INDEX(Dim_Product!$B:B, MATCH($A12,Dim_Product!$A:$A,0)) -> Ribbed Jersey Top | D12: =INDEX(Dim_Product!$D:D, MATCH($A12,Dim_Product!$A:$A,0)) -> Tops | E12: =INDEX(Dim_Product!$E:E, MATCH($A12,Dim_Product!$A:$A,0)) -> Sand | F12: =INDEX(Dim_Product!$F:F, MATCH($A12,Dim_Product!$A:$A,0)) -> Core | G12: =INDEX(Dim_Product!$G:G, MATCH($A12,Dim_Product!$A:$A,0)) -> 17.99 | H12: =SUMIFS(Fact_Weekly!$D$2:$D$1500,Fact_Weekly!$B$2:$B$1500,$A12,Fact_Weekly!$C$2:$C$1500,$B12) -> 142 | I12: =SUMIFS(Fact_Weekly!$E$2:$E$1500,Fact_Weekly!$B$2:$B$1500,$A12,Fact_Weekly!$C$2:$C$1500,$B12) -> 141 | J12: =H12-I12 -> 1 | K12: =IF(H12>0,I12/H12,0) -> 0.99295775 | L12: =SUMIFS(Fact_Weekly!$E$2:$E$1500,Fact_Weekly!$B$2:$B$1500,$A12,Fact_Weekly!$C$2:$C$1500,$B12,Fact_Weekly!$A$2:$A$1500,">="&(Assumptions!$B$12-Assumptions!$B$11+1)) -> 48 | M12: =L12/Assumptions!$B$11 -> 12 | N12: =COUNTIFS(Fact_Weekly!$B$2:$B$1500,$A12,Fact_Weekly!$C$2:$C$1500,$B12,Fact_Weekly!$G$2:$G$1500,">0") -> 12 | O12: =IF(N12>0,I12/N12,0) -> 11.75 | P12: =IF(M12>0,J12/M12,IF(J12>0,Assumptions!$B$12,0)) -> 0.083333333 | Q12: =IF(AND(N12<Assumptions!$B$12,K12>=0.99),1,0) -> 0 | R12: =IF(Q12=1,O12,M12) -> 12 | S12: =IF(Q12=1,(Assumptions!$B$12-N12)*(H12/Assumptions!$B$12),0) -> 0 | T12: =S12*G12 -> 0 | U12: =IF(OR(K12>=Assumptions!$B$5,Q12=1,AND(F12="Core",P12<Assumptions!$B$7)),1,0) -> 1 | V12: =IF(AND(F12="Seasonal",K12<Assumptions!$B$6,P12>Assumptions!$B$8),1,0) -> 0 | W12: =IF(U12=1,ROUND(MAX(0,Assumptions!$B$9*R12-J12),0),0) -> 71 | X12: =IF(V12=1,"Markdown / clear",IF(AND(U12=1,Q12=1),"Reorder - recover lost sales",IF(U12=1,"Reorder / replenish","Maintain / monitor"))) -> Reorder / replenish
A13: VS-101-SAN | B13: Marketplace Gamma | C13: =INDEX(Dim_Product!$B:B, MATCH($A13,Dim_Product!$A:$A,0)) -> Ribbed Jersey Top | D13: =INDEX(Dim_Product!$D:D, MATCH($A13,Dim_Product!$A:$A,0)) -> Tops | E13: =INDEX(Dim_Product!$E:E, MATCH($A13,Dim_Product!$A:$A,0)) -> Sand | F13: =INDEX(Dim_Product!$F:F, MATCH($A13,Dim_Product!$A:$A,0)) -> Core | G13: =INDEX(Dim_Product!$G:G, MATCH($A13,Dim_Product!$A:$A,0)) -> 17.99 | H13: =SUMIFS(Fact_Weekly!$D$2:$D$1500,Fact_Weekly!$B$2:$B$1500,$A13,Fact_Weekly!$C$2:$C$1500,$B13) -> 191 | I13: =SUMIFS(Fact_Weekly!$E$2:$E$1500,Fact_Weekly!$B$2:$B$1500,$A13,Fact_Weekly!$C$2:$C$1500,$B13) -> 186 | J13: =H13-I13 -> 5 | K13: =IF(H13>0,I13/H13,0) -> 0.97382199 | L13: =SUMIFS(Fact_Weekly!$E$2:$E$1500,Fact_Weekly!$B$2:$B$1500,$A13,Fact_Weekly!$C$2:$C$1500,$B13,Fact_Weekly!$A$2:$A$1500,">="&(Assumptions!$B$12-Assumptions!$B$11+1)) -> 66 | M13: =L13/Assumptions!$B$11 -> 16.5 | N13: =COUNTIFS(Fact_Weekly!$B$2:$B$1500,$A13,Fact_Weekly!$C$2:$C$1500,$B13,Fact_Weekly!$G$2:$G$1500,">0") -> 12 | O13: =IF(N13>0,I13/N13,0) -> 15.5 | P13: =IF(M13>0,J13/M13,IF(J13>0,Assumptions!$B$12,0)) -> 0.3030303 | Q13: =IF(AND(N13<Assumptions!$B$12,K13>=0.99),1,0) -> 0 | R13: =IF(Q13=1,O13,M13) -> 16.5 | S13: =IF(Q13=1,(Assumptions!$B$12-N13)*(H13/Assumptions!$B$12),0) -> 0 | T13: =S13*G13 -> 0 | U13: =IF(OR(K13>=Assumptions!$B$5,Q13=1,AND(F13="Core",P13<Assumptions!$B$7)),1,0) -> 1 | V13: =IF(AND(F13="Seasonal",K13<Assumptions!$B$6,P13>Assumptions!$B$8),1,0) -> 0 | W13: =IF(U13=1,ROUND(MAX(0,Assumptions!$B$9*R13-J13),0),0) -> 94 | X13: =IF(V13=1,"Markdown / clear",IF(AND(U13=1,Q13=1),"Reorder - recover lost sales",IF(U13=1,"Reorder / replenish","Maintain / monitor"))) -> Reorder / replenish
... A121: VS-303-KHA | B121: Marketplace Gamma | C121: =INDEX(Dim_Product!$B:B, MATCH($A121,Dim_Product!$A:$A,0)) -> Belted Trench Coat | D121: =INDEX(Dim_Product!$D:D, MATCH($A121,Dim_Product!$A:$A,0)) -> Outerwear | E121: =INDEX(Dim_Product!$E:E, MATCH($A121,Dim_Product!$A:$A,0)) -> Khaki | F121: =INDEX(Dim_Product!$F:F, MATCH($A121,Dim_Product!$A:$A,0)) -> Seasonal | G121: =INDEX(Dim_Product!$G:G, MATCH($A121,Dim_Product!$A:$A,0)) -> 79.99 | H121: =SUMIFS(Fact_Weekly!$D$2:$D$1500,Fact_Weekly!$B$2:$B$1500,$A121,Fact_Weekly!$C$2:$C$1500,$B121) -> 136 | I121: =SUMIFS(Fact_Weekly!$E$2:$E$1500,Fact_Weekly!$B$2:$B$1500,$A121,Fact_Weekly!$C$2:$C$1500,$B121) -> 99 | J121: =H121-I121 -> 37 | K121: =IF(H121>0,I121/H121,0) -> 0.72794118 | L121: =SUMIFS(Fact_Weekly!$E$2:$E$1500,Fact_Weekly!$B$2:$B$1500,$A121,Fact_Weekly!$C$2:$C$1500,$B121,Fact_Weekly!$A$2:$A$1500,">="&(Assumptions!$B$12-Assumptions!$B$11+1)) -> 33 | M121: =L121/Assumptions!$B$11 -> 8.25 | N121: =COUNTIFS(Fact_Weekly!$B$2:$B$1500,$A121,Fact_Weekly!$C$2:$C$1500,$B121,Fact_Weekly!$G$2:$G$1500,">0") -> 12 | O121: =IF(N121>0,I121/N121,0) -> 8.25 | P121: =IF(M121>0,J121/M121,IF(J121>0,Assumptions!$B$12,0)) -> 4.4848485 | Q121: =IF(AND(N121<Assumptions!$B$12,K121>=0.99),1,0) -> 0 | R121: =IF(Q121=1,O121,M121) -> 8.25 | S121: =IF(Q121=1,(Assumptions!$B$12-N121)*(H121/Assumptions!$B$12),0) -> 0 | T121: =S121*G121 -> 0 | U121: =IF(OR(K121>=Assumptions!$B$5,Q121=1,AND(F121="Core",P121<Assumptions!$B$7)),1,0) -> 0 | V121: =IF(AND(F121="Seasonal",K121<Assumptions!$B$6,P121>Assumptions!$B$8),1,0) -> 0 | W121: =IF(U121=1,ROUND(MAX(0,Assumptions!$B$9*R121-J121),0),0) -> 0 | X121: =IF(V121=1,"Markdown / clear",IF(AND(U121=1,Q121=1),"Reorder - recover lost sales",IF(U121=1,"Reorder / replenish","Maintain / monitor"))) -> Maintain / monitor
